elb_provider/elb_provider.py
elb_provider/manifest.toml
elb_provider/test_elb_provider.py
opsbox_elb_provider-0.1.7.dist-info/LICENCE.txt
opsbox_elb_provider-0.1.7.dist-info/METADATA
opsbox_elb_provider-0.1.7.dist-info/WHEEL
opsbox_elb_provider-0.1.7.dist-info/entry_points.txt
opsbox_elb_provider-0.1.7.dist-info/top_level.txt
opsbox_elb_provider-0.1.7.dist-info/RECORD
